dffml_model_vowpalWabbit/__init__.py
dffml_model_vowpalWabbit/version.py
dffml_model_vowpalWabbit/vw_base.py
tests/__init__.py
tests/test_vw.py
tests/test_vw_integration.py
dffml_model_vowpalWabbit-0.1.0.post0.dist-info/LICENSE
dffml_model_vowpalWabbit-0.1.0.post0.dist-info/METADATA
dffml_model_vowpalWabbit-0.1.0.post0.dist-info/WHEEL
dffml_model_vowpalWabbit-0.1.0.post0.dist-info/entry_points.txt
dffml_model_vowpalWabbit-0.1.0.post0.dist-info/top_level.txt
dffml_model_vowpalWabbit-0.1.0.post0.dist-info/RECORD
